<annotation>
	<folder>0</folder>
	<filename>1597920389444.jpg</filename>
	<path>C:\Users\A752932\OneDrive - Atos\Documents\projects\AI4EU\data\20201204 - SMR\assignOld\0\1597920389444.jpg</path>
	<source>
		<database>Unknown</database>
	</source>
	<size>
		<width>4032</width>
		<height>3024</height>
		<depth>3</depth>
	</size>
	<segmented>0</segmented>
	<object>
		<name>grapes</name>
		<pose>Unspecified</pose>
		<truncated>0</truncated>
		<difficult>0</difficult>
		<bndbox>
			<xmin>302</xmin>
			<ymin>1421</ymin>
			<xmax>385</xmax>
			<ymax>1489</ymax>
		</bndbox>
	</object>
	<object>
		<name>grapes</name>
		<pose>Unspecified</pose>
		<truncated>0</truncated>
		<difficult>0</difficult>
		<bndbox>
			<xmin>712</xmin>
			<ymin>1066</ymin>
			<xmax>809</xmax>
			<ymax>1169</ymax>
		</bndbox>
	</object>
	<object>
		<name>grapes</name>
		<pose>Unspecified</pose>
		<truncated>0</truncated>
		<difficult>0</difficult>
		<bndbox>
			<xmin>232</xmin>
			<ymin>1133</ymin>
			<xmax>299</xmax>
			<ymax>1206</ymax>
		</bndbox>
	</object>
	<object>
		<name>grapes</name>
		<pose>Unspecified</pose>
		<truncated>0</truncated>
		<difficult>0</difficult>
		<bndbox>
			<xmin>1121</xmin>
			<ymin>1166</ymin>
			<xmax>1173</xmax>
			<ymax>1197</ymax>
		</bndbox>
	</object>
	<object>
		<name>grapes</name>
		<pose>Unspecified</pose>
		<truncated>0</truncated>
		<difficult>0</difficult>
		<bndbox>
			<xmin>1154</xmin>
			<ymin>969</ymin>
			<xmax>1262</xmax>
			<ymax>1084</ymax>
		</bndbox>
	</object>
	<object>
		<name>grapes</name>
		<pose>Unspecified</pose>
		<truncated>0</truncated>
		<difficult>0</difficult>
		<bndbox>
			<xmin>1454</xmin>
			<ymin>814</ymin>
			<xmax>1559</xmax>
			<ymax>928</ymax>
		</bndbox>
	</object>
	<object>
		<name>grapes</name>
		<pose>Unspecified</pose>
		<truncated>0</truncated>
		<difficult>0</difficult>
		<bndbox>
			<xmin>1728</xmin>
			<ymin>1340</ymin>
			<xmax>1829</xmax>
			<ymax>1459</ymax>
		</bndbox>
	</object>
	<object>
		<name>grapes</name>
		<pose>Unspecified</pose>
		<truncated>0</truncated>
		<difficult>0</difficult>
		<bndbox>
			<xmin>1883</xmin>
			<ymin>1106</ymin>
			<xmax>2028</xmax>
			<ymax>1398</ymax>
		</bndbox>
	</object>
	<object>
		<name>grapes</name>
		<pose>Unspecified</pose>
		<truncated>0</truncated>
		<difficult>0</difficult>
		<bndbox>
			<xmin>1832</xmin>
			<ymin>961</ymin>
			<xmax>1922</xmax>
			<ymax>1072</ymax>
		</bndbox>
	</object>
	<object>
		<name>grapes</name>
		<pose>Unspecified</pose>
		<truncated>0</truncated>
		<difficult>0</difficult>
		<bndbox>
			<xmin>2126</xmin>
			<ymin>1370</ymin>
			<xmax>2261</xmax>
			<ymax>1611</ymax>
		</bndbox>
	</object>
	<object>
		<name>grapes</name>
		<pose>Unspecified</pose>
		<truncated>0</truncated>
		<difficult>0</difficult>
		<bndbox>
			<xmin>2305</xmin>
			<ymin>1221</ymin>
			<xmax>2390</xmax>
			<ymax>1320</ymax>
		</bndbox>
	</object>
	<object>
		<name>grapes</name>
		<pose>Unspecified</pose>
		<truncated>0</truncated>
		<difficult>0</difficult>
		<bndbox>
			<xmin>2302</xmin>
			<ymin>1423</ymin>
			<xmax>2362</xmax>
			<ymax>1542</ymax>
		</bndbox>
	</object>
	<object>
		<name>grapes</name>
		<pose>Unspecified</pose>
		<truncated>0</truncated>
		<difficult>0</difficult>
		<bndbox>
			<xmin>2511</xmin>
			<ymin>1292</ymin>
			<xmax>2570</xmax>
			<ymax>1364</ymax>
		</bndbox>
	</object>
	<object>
		<name>grapes</name>
		<pose>Unspecified</pose>
		<truncated>0</truncated>
		<difficult>0</difficult>
		<bndbox>
			<xmin>2496</xmin>
			<ymin>1394</ymin>
			<xmax>2589</xmax>
			<ymax>1451</ymax>
		</bndbox>
	</object>
	<object>
		<name>grapes</name>
		<pose>Unspecified</pose>
		<truncated>0</truncated>
		<difficult>0</difficult>
		<bndbox>
			<xmin>2526</xmin>
			<ymin>1470</ymin>
			<xmax>2633</xmax>
			<ymax>1611</ymax>
		</bndbox>
	</object>
	<object>
		<name>grapes</name>
		<pose>Unspecified</pose>
		<truncated>0</truncated>
		<difficult>0</difficult>
		<bndbox>
			<xmin>2660</xmin>
			<ymin>1393</ymin>
			<xmax>2729</xmax>
			<ymax>1492</ymax>
		</bndbox>
	</object>
	<object>
		<name>grapes</name>
		<pose>Unspecified</pose>
		<truncated>0</truncated>
		<difficult>0</difficult>
		<bndbox>
			<xmin>2580</xmin>
			<ymin>1092</ymin>
			<xmax>2752</xmax>
			<ymax>1243</ymax>
		</bndbox>
	</object>
	<object>
		<name>grapes</name>
		<pose>Unspecified</pose>
		<truncated>0</truncated>
		<difficult>0</difficult>
		<bndbox>
			<xmin>2827</xmin>
			<ymin>1310</ymin>
			<xmax>2987</xmax>
			<ymax>1626</ymax>
		</bndbox>
	</object>
	<object>
		<name>grapes</name>
		<pose>Unspecified</pose>
		<truncated>0</truncated>
		<difficult>0</difficult>
		<bndbox>
			<xmin>2889</xmin>
			<ymin>1138</ymin>
			<xmax>3074</xmax>
			<ymax>1333</ymax>
		</bndbox>
	</object>
	<object>
		<name>grapes</name>
		<pose>Unspecified</pose>
		<truncated>0</truncated>
		<difficult>0</difficult>
		<bndbox>
			<xmin>3084</xmin>
			<ymin>1564</ymin>
			<xmax>3138</xmax>
			<ymax>1677</ymax>
		</bndbox>
	</object>
	<object>
		<name>grapes</name>
		<pose>Unspecified</pose>
		<truncated>0</truncated>
		<difficult>0</difficult>
		<bndbox>
			<xmin>3204</xmin>
			<ymin>1600</ymin>
			<xmax>3365</xmax>
			<ymax>1781</ymax>
		</bndbox>
	</object>
	<object>
		<name>grapes</name>
		<pose>Unspecified</pose>
		<truncated>0</truncated>
		<difficult>0</difficult>
		<bndbox>
			<xmin>376</xmin>
			<ymin>945</ymin>
			<xmax>438</xmax>
			<ymax>1010</ymax>
		</bndbox>
	</object>
</annotation>
